lmfao/__init__.py
lmfao/factory.py
lmfao/adapters/__init__.py
lmfao/adapters/base.py
lmfao/adapters/chatbot.py
lmfao/adapters/classification.py
lmfao/adapters/client_mixins.py
lmfao/adapters/fermi.py
lmfao/clients/__init__.py
lmfao/clients/anthropic.py
lmfao/clients/base.py
lmfao/clients/cohere.py
lmfao/clients/openai.py
lmfao/clients/utils.py
lmfao/clients/schemas/__init__.py
lmfao/clients/schemas/anthropic.py
lmfao/clients/schemas/base.py
lmfao/clients/schemas/cohere.py
lmfao/clients/schemas/openai.py
lmfao/orchestrators/__init__.py
lmfao/orchestrators/base.py
lmfao/prompters/__init__.py
lmfao/prompters/base.py
lmfao/prompters/classification.py
lmfao/prompters/fermi.py
lmfao/tasks/__init__.py
lmfao/tasks/base.py
lmfao/tasks/chatbot.py
lmfao/tasks/classification.py
lmfao/tasks/fermi.py
lmfao-0.0.1b1.dist-info/LICENSE
lmfao-0.0.1b1.dist-info/METADATA
lmfao-0.0.1b1.dist-info/WHEEL
lmfao-0.0.1b1.dist-info/top_level.txt
lmfao-0.0.1b1.dist-info/RECORD
